nb_aiopool/__init__.py
nb_aiopool/nb_aiopool.py
nb_aiopool/contrib/README.md
nb_aiopool/contrib/__init__.py
nb_aiopool/contrib/example.py
nb_aiopool/contrib/nb_aio_task.py
nb_aiopool-1.0.dist-info/METADATA
nb_aiopool-1.0.dist-info/WHEEL
nb_aiopool-1.0.dist-info/top_level.txt
nb_aiopool-1.0.dist-info/RECORD
