Metadata-Version: 2.1
Name: nb-aiopool
Version: 1.0
Summary: 即使在 asyncio 编程生态中，并发池仍然有其用武之地。nb_aiopool 提供并发限制和背压机制
Author-email: ydf0509 <ydf0509@xxx.com>
License: MIT
Project-URL: Homepage, https://github.com/ydf0509/nb_aiopool
Project-URL: Repository, https://github.com/ydf0509/nb_aiopool
Project-URL: Issues, https://github.com/ydf0509/nb_aiopool/issues
Keywords: asyncio,pool,concurrency,task,async,asyncio-pool,asyncio-concurrency,asyncio-task,asyncio-concurrent,asyncio-pool-concurrency,asyncio-pool-task,asyncio-pool-concurrent
Classifier: Development Status :: 3 - Alpha
Classifier: Intended Audience :: Developers
Classifier: License :: OSI Approved :: MIT License
Classifier: Programming Language :: Python :: 3
Classifier: Programming Language :: Python :: 3.7
Classifier: Programming Language :: Python :: 3.8
Classifier: Programming Language :: Python :: 3.9
Classifier: Programming Language :: Python :: 3.10
Classifier: Programming Language :: Python :: 3.11
Classifier: Programming Language :: Python :: 3.12
Classifier: Programming Language :: Python :: 3.13
Classifier: Programming Language :: Python :: 3.14
Requires-Python: >=3.7
Requires-Dist: typing-extensions >=3.7 ; python_version < "3.8"
Provides-Extra: dev
Requires-Dist: black >=21.0 ; extra == 'dev'
Requires-Dist: flake8 >=3.8 ; extra == 'dev'
Requires-Dist: mypy >=0.812 ; extra == 'dev'
Provides-Extra: test
Requires-Dist: pytest >=6.0 ; extra == 'test'
Requires-Dist: pytest-asyncio >=0.14 ; extra == 'test'
